{"groups":[{"name":"Hero","titleid":6731207,"statlistscollection":[{"arrangebyfield":"xuid","arrangebyfieldid":2533274845176708,"stats":[{"groupproperties":{"Ordinal":1,"SortOrder":"Descending","DisplayName":"Shards Collected","DisplayFormat":"Integer","DisplaySemantic":"Tier"},"xuid":2533274845176708,"scid":"8b6a0100-7ed9-41d4-a58a-18930066b5c7","name":"ShardsCollected","type":"Integer","value":25,"properties":{"DisplayName":"Shards Collected"}},{"groupproperties":{"Ordinal":2,"SortOrder":"Descending","DisplayName":"Letters Collected","DisplayFormat":"Integer","DisplaySemantic":"Tier"},"xuid":2533274845176708,"scid":"8b6a0100-7ed9-41d4-a58a-18930066b5c7","name":"LettersCollected","type":"Integer","value":12,"properties":{"DisplayName":"Letters Collected"}},{"groupproperties":{"Ordinal":3,"SortOrder":"Descending","DisplayName":"Crows Killed","DisplayFormat":"Integer","DisplaySemantic":"Tier"},"xuid":2533274845176708,"scid":"8b6a0100-7ed9-41d4-a58a-18930066b5c7","name":"CrowsKilled","type":"Integer","value":37,"properties":{"DisplayName":"Crows Killed"}}]}]}],"statlistscollection":[{"arrangebyfield":"xuid","arrangebyfieldid":2533274845176708,"stats":[{"groupproperties":[],"xuid":2533274845176708,"scid":"8b6a0100-7ed9-41d4-a58a-18930066b5c7","titleid":6731207,"name":"MinutesPlayed","type":"Integer","value":248,"properties":[]},{"groupproperties":[],"xuid":2533274845176708,"scid":"8b6a0100-7ed9-41d4-a58a-18930066b5c7","titleid":6731207,"name":"GameProgress","type":"Double","properties":[]}]}]}