{"groups":[{"name":"Hero","titleid":20605635,"statlistscollection":[{"arrangebyfield":"xuid","arrangebyfieldid":2533274845176708,"stats":[{"groupproperties":{"Ordinal":1,"SortOrder":"Descending","DisplayName":"Power Core Level","DisplayFormat":"Integer","DisplaySemantic":"Tier"},"xuid":2533274845176708,"scid":"f5030100-d7c2-4c0f-941b-a698013a6ac3","name":"CoreLevel","type":"Integer","value":41,"properties":{"DisplayName":"Power Core Level"}},{"groupproperties":{"Ordinal":2,"SortOrder":"Descending","DisplayName":"Body parts cut","DisplayFormat":"Integer","DisplaySemantic":"Cumulative"},"xuid":2533274845176708,"scid":"f5030100-d7c2-4c0f-941b-a698013a6ac3","name":"LimbsCut","type":"Integer","value":257,"properties":{"DisplayName":"Body parts cut"}},{"groupproperties":{"Ordinal":3,"SortOrder":"Descending","DisplayName":"Enemies killed","DisplayFormat":"Integer","DisplaySemantic":"Cumulative"},"xuid":2533274845176708,"scid":"f5030100-d7c2-4c0f-941b-a698013a6ac3","name":"EnemyDefeats","type":"Integer","value":693,"properties":{"DisplayName":"Enemies killed"}},{"groupproperties":{"Ordinal":4,"SortOrder":"Ascending","DisplayName":"Player deaths","DisplayFormat":"Integer","DisplaySemantic":"Cumulative"},"xuid":2533274845176708,"scid":"f5030100-d7c2-4c0f-941b-a698013a6ac3","name":"PlayerDefeats","type":"Integer","value":147,"properties":{"DisplayName":"Player deaths"}},{"groupproperties":{"Ordinal":5,"SortOrder":"Descending","DisplayName":"Highest amount of Tech Scrap","DisplayFormat":"Integer","DisplaySemantic":"Best"},"xuid":2533274845176708,"scid":"f5030100-d7c2-4c0f-941b-a698013a6ac3","name":"MaxTechscrap","type":"Integer","value":10200,"properties":{"DisplayName":"Highest amount of Tech Scrap"}}]}]}],"statlistscollection":[{"arrangebyfield":"xuid","arrangebyfieldid":2533274845176708,"stats":[{"groupproperties":[],"xuid":2533274845176708,"scid":"f5030100-d7c2-4c0f-941b-a698013a6ac3","titleid":20605635,"name":"MinutesPlayed","type":"Integer","value":730,"properties":[]},{"groupproperties":[],"xuid":2533274845176708,"scid":"f5030100-d7c2-4c0f-941b-a698013a6ac3","titleid":20605635,"name":"GameProgress","type":"Double","properties":[]}]}]}