{"groups":[{"name":"Hero","titleid":89165390,"statlistscollection":[{"arrangebyfield":"xuid","arrangebyfieldid":2533274845176708,"stats":[{"groupproperties":{"Ordinal":1,"SortOrder":"Descending","DisplayName":"Runs Completed","DisplayFormat":"Integer","DisplaySemantic":"Cumulative"},"xuid":2533274845176708,"scid":"faa90100-64d2-4520-bccf-790405508e4e","name":"SessionsCompleted","type":"Integer","value":4,"properties":{"DisplayName":"Runs Completed"}},{"groupproperties":{"Ordinal":2,"SortOrder":"Descending","DisplayName":"Sentries Killed","DisplayFormat":"Integer","DisplaySemantic":"Cumulative"},"xuid":2533274845176708,"scid":"faa90100-64d2-4520-bccf-790405508e4e","name":"EnemyKillsSentry","type":"Integer","value":39,"properties":{"DisplayName":"Sentries Killed"}},{"groupproperties":{"Ordinal":3,"SortOrder":"Descending","DisplayName":"Best Run Score","DisplayFormat":"Integer","DisplaySemantic":"Best"},"xuid":2533274845176708,"scid":"faa90100-64d2-4520-bccf-790405508e4e","name":"RunScoreMax","type":"Integer","value":2686009,"properties":{"DisplayName":"Best Run Score"}},{"groupproperties":{"Ordinal":4,"SortOrder":"Descending","DisplayName":"Grid Bugs Killed","DisplayFormat":"Integer","DisplaySemantic":"Cumulative"},"xuid":2533274845176708,"scid":"faa90100-64d2-4520-bccf-790405508e4e","name":"EnemyKillsGridBug","type":"Integer","value":59,"properties":{"DisplayName":"Grid Bugs Killed"}},{"groupproperties":{"Ordinal":5,"SortOrder":"Descending","DisplayName":"Highest Combo","DisplayFormat":"Integer","DisplaySemantic":"Best"},"xuid":2533274845176708,"scid":"faa90100-64d2-4520-bccf-790405508e4e","name":"ComboMax","type":"Integer","value":279,"properties":{"DisplayName":"Highest Combo"}}]}]}],"statlistscollection":[{"arrangebyfield":"xuid","arrangebyfieldid":2533274845176708,"stats":[{"groupproperties":[],"xuid":2533274845176708,"scid":"faa90100-64d2-4520-bccf-790405508e4e","titleid":89165390,"name":"MinutesPlayed","type":"Integer","value":34,"properties":[]},{"groupproperties":[],"xuid":2533274845176708,"scid":"faa90100-64d2-4520-bccf-790405508e4e","titleid":89165390,"name":"GameProgress","type":"Double","value":5.2083335,"properties":[]}]}]}