{"groups":[{"name":"Hero","titleid":820078969,"statlistscollection":[{"arrangebyfield":"xuid","arrangebyfieldid":2533274845176708,"stats":[{"groupproperties":{"Ordinal":1,"SortOrder":"Descending","DisplayName":"Total zombie kills","DisplayFormat":"Integer","DisplaySemantic":"Best"},"xuid":2533274845176708,"scid":"56ed0100-1d50-4e91-9a1a-911c30e16979","name":"EnemyDefeats","type":"Integer","value":444,"properties":{"DisplayName":"Total zombie kills"}},{"groupproperties":{"Ordinal":2,"SortOrder":"Descending","DisplayName":"Total zombie spawners destroyed","DisplayFormat":"Integer","DisplaySemantic":"Best"},"xuid":2533274845176708,"scid":"56ed0100-1d50-4e91-9a1a-911c30e16979","name":"HatcherKill","type":"Integer","properties":{"DisplayName":"Total zombie spawners destroyed"}},{"groupproperties":{"Ordinal":3,"SortOrder":"Descending","DisplayName":"Best combo","DisplayFormat":"Integer","DisplaySemantic":"Best"},"xuid":2533274845176708,"scid":"56ed0100-1d50-4e91-9a1a-911c30e16979","name":"Combo","type":"Integer","value":735,"properties":{"DisplayName":"Best combo"}},{"groupproperties":{"Ordinal":4,"SortOrder":"Descending","DisplayName":"Slaughter mode highscore","DisplayFormat":"Integer","DisplaySemantic":"Best"},"xuid":2533274845176708,"scid":"56ed0100-1d50-4e91-9a1a-911c30e16979","name":"SlaughterPoints","type":"Integer","properties":{"DisplayName":"Slaughter mode highscore"}},{"groupproperties":{"Ordinal":5,"SortOrder":"Descending","DisplayName":"Total objects destroyed","DisplayFormat":"Integer","DisplaySemantic":"Best"},"xuid":2533274845176708,"scid":"56ed0100-1d50-4e91-9a1a-911c30e16979","name":"DestroyProps","type":"Integer","value":93,"properties":{"DisplayName":"Total objects destroyed"}},{"groupproperties":{"Ordinal":6,"SortOrder":"Descending","DisplayName":"Total Blood Race opponents killed","DisplayFormat":"Integer","DisplaySemantic":"Best"},"xuid":2533274845176708,"scid":"56ed0100-1d50-4e91-9a1a-911c30e16979","name":"KillBots","type":"Integer","properties":{"DisplayName":"Total Blood Race opponents killed"}}]}]}],"statlistscollection":[{"arrangebyfield":"xuid","arrangebyfieldid":2533274845176708,"stats":[{"groupproperties":[],"xuid":2533274845176708,"scid":"56ed0100-1d50-4e91-9a1a-911c30e16979","titleid":820078969,"name":"MinutesPlayed","type":"Integer","value":10,"properties":[]},{"groupproperties":[],"xuid":2533274845176708,"scid":"56ed0100-1d50-4e91-9a1a-911c30e16979","titleid":820078969,"name":"GameProgress","type":"Double","value":3.2258062,"properties":[]}]}]}