{"groups":[{"name":"Hero","titleid":1482870140,"statlistscollection":[{"arrangebyfield":"xuid","arrangebyfieldid":2533274845176708,"stats":[{"groupproperties":{"Ordinal":1,"SortOrder":"Descending","DisplayName":"Mastery Rank"},"xuid":2533274845176708,"scid":"a2b70100-d7d8-4f43-8a59-dd4a5862cd7c","name":"Max.Tag.PLAYERRANK","type":"Integer","value":2,"properties":{"DisplayName":"Mastery Rank"}},{"groupproperties":{"Ordinal":2,"SortOrder":"Descending","DisplayName":"Items Crafted"},"xuid":2533274845176708,"scid":"a2b70100-d7d8-4f43-8a59-dd4a5862cd7c","name":"Count.Tag.ITEMCRAFTED","type":"Integer","value":2,"properties":{"DisplayName":"Items Crafted"}},{"groupproperties":{"Ordinal":3,"SortOrder":"Descending","DisplayName":"Warframes Owned"},"xuid":2533274845176708,"scid":"a2b70100-d7d8-4f43-8a59-dd4a5862cd7c","name":"Max.Tag.POWERSUITCOUNT","type":"Integer","value":1,"properties":{"DisplayName":"Warframes Owned"}},{"groupproperties":{"Ordinal":4,"SortOrder":"Descending","DisplayName":"Sentinels Owned"},"xuid":2533274845176708,"scid":"a2b70100-d7d8-4f43-8a59-dd4a5862cd7c","name":"Max.Tag.SENTINELCOUNT","type":"Integer","value":0,"properties":{"DisplayName":"Sentinels Owned"}},{"groupproperties":{"Ordinal":5,"SortOrder":"Descending","DisplayName":"Mods Applied"},"xuid":2533274845176708,"scid":"a2b70100-d7d8-4f43-8a59-dd4a5862cd7c","name":"Max.Tag.ITEMUPGRADECOUNT","type":"Integer","value":7,"properties":{"DisplayName":"Mods Applied"}},{"groupproperties":{"Ordinal":6,"SortOrder":"Descending","DisplayName":"Ciphers Solved"},"xuid":2533274845176708,"scid":"a2b70100-d7d8-4f43-8a59-dd4a5862cd7c","name":"Count.Tag.CIPHERSOLVED","type":"Integer","value":37,"properties":{"DisplayName":"Ciphers Solved"}}]}]}],"statlistscollection":[{"arrangebyfield":"xuid","arrangebyfieldid":2533274845176708,"stats":[{"groupproperties":[],"xuid":2533274845176708,"scid":"a2b70100-d7d8-4f43-8a59-dd4a5862cd7c","titleid":1482870140,"name":"MinutesPlayed","type":"Integer","value":608,"properties":[]},{"groupproperties":[],"xuid":2533274845176708,"scid":"a2b70100-d7d8-4f43-8a59-dd4a5862cd7c","titleid":1482870140,"name":"GameProgress","type":"Double","value":1.5122471,"properties":[]}]}]}