{"titles":[{"lastUnlock":"2018-06-17T17:43:09.7570000Z","titleId":6731207,"serviceConfigId":"8b6a0100-7ed9-41d4-a58a-18930066b5c7","titleType":"DGame","platform":"Durango","name":"Albert and Otto","earnedAchievements":5,"currentGamerscore":250,"maxGamerscore":1000},{"lastUnlock":"2016-09-11T12:25:10.6860000Z","titleId":10027721,"serviceConfigId":"28dd0100-1521-414e-a1d8-f0ba009902c9","titleType":"Game","platform":"XboxOne","name":"The Fall","earnedAchievements":7,"currentGamerscore":425,"maxGamerscore":1000},{"lastUnlock":"2016-01-01T10:51:08.0185988Z","titleId":16468936,"serviceConfigId":"3e770100-834e-4b82-b82c-689a00fb4bc8","titleType":"Game","platform":"XboxOne","name":"So Many Me","earnedAchievements":1,"currentGamerscore":10,"maxGamerscore":1000},{"lastUnlock":"2017-12-03T13:59:03.4530000Z","titleId":20605635,"serviceConfigId":"f5030100-d7c2-4c0f-941b-a698013a6ac3","titleType":"DGame","platform":"Durango","name":"The Surge","earnedAchievements":11,"currentGamerscore":180,"maxGamerscore":1400},{"lastUnlock":"2016-03-15T14:23:37.3996809Z","titleId":21560138,"serviceConfigId":"33e50100-4011-4ed1-9df7-03550148fb4a","titleType":"DGame","platform":"Durango","name":"Sheltered","earnedAchievements":9,"currentGamerscore":145,"maxGamerscore":1000},{"lastUnlock":"2016-07-31T07:51:27.0972482Z","titleId":29720212,"serviceConfigId":"76490100-087c-48b9-a5cc-975701c57e94","titleType":"Game","platform":"XboxOne","name":"The Flame in the Flood","earnedAchievements":4,"currentGamerscore":80,"maxGamerscore":1000},{"lastUnlock":"2018-04-23T17:38:23.0150000Z","titleId":48906653,"serviceConfigId":"bf920100-d19f-444b-8a48-95b402ea419d","titleType":"Game","platform":"XboxOne","name":"Has-Been Heroes","earnedAchievements":1,"currentGamerscore":15,"maxGamerscore":1000},{"lastUnlock":"2017-03-01T21:35:52.2010000Z","titleId":52417526,"serviceConfigId":"87ee0100-bb7a-4584-b4bb-4358031fd3f6","titleType":"Game","platform":"XboxOne","name":"Candleman","earnedAchievements":10,"currentGamerscore":1000,"maxGamerscore":1500},{"lastUnlock":"2018-03-31T07:40:56.2700000Z","titleId":52523189,"serviceConfigId":"cb2c0100-03d5-4913-8391-3f20032170b5","titleType":"DGame","platform":"Durango","name":"TRIALS OF THE BLOOD DRAGON","earnedAchievements":1,"currentGamerscore":20,"maxGamerscore":1000},{"lastUnlock":"2017-04-26T16:42:24.6200000Z","titleId":55549300,"serviceConfigId":"660d0100-f9c6-494f-bfc7-bc31034f9d74","titleType":"Game","platform":"XboxOne","name":"Axiom Verge","earnedAchievements":3,"currentGamerscore":45,"maxGamerscore":1000},{"lastUnlock":"2016-01-07T17:35:06.8081814Z","titleId":58472989,"serviceConfigId":"5af40b00-965f-4a28-aab5-cf69642bec88","titleType":"DGame","platform":"Durango","name":"Killer Instinct","earnedAchievements":13,"currentGamerscore":105,"maxGamerscore":4935},{"lastUnlock":"2018-02-22T18:29:45.8070000Z","titleId":62357364,"serviceConfigId":"9aab0100-e522-4dba-82d0-503103b77f74","titleType":"Game","platform":"XboxOne","name":"The Fall Part 2: Unbound","earnedAchievements":23,"currentGamerscore":625,"maxGamerscore":1000},{"lastUnlock":"2016-07-16T21:26:31.1005942Z","titleId":70112963,"serviceConfigId":"44e00100-600d-4c85-8cf3-5e6d042dd6c3","titleType":"Game","platform":"XboxOne","name":"Knight Squad","earnedAchievements":1,"currentGamerscore":0,"maxGamerscore":1000},{"lastUnlock":"2016-03-12T15:25:12.4796901Z","titleId":74304278,"serviceConfigId":"e2f10100-3928-4019-8789-5f12046dcb16","titleType":"DGame","platform":"Durango","name":"Tom Clancy's The Division","earnedAchievements":4,"currentGamerscore":30,"maxGamerscore":1450},{"lastUnlock":"2017-06-11T12:54:35.8250000Z","titleId":78625846,"serviceConfigId":"4b910100-214e-472d-9b06-96da04afbc36","titleType":"Game","platform":"XboxOne","name":"forma.8","earnedAchievements":5,"currentGamerscore":100,"maxGamerscore":1000},{"lastUnlock":"2018-12-01T18:52:51.5370000Z","titleId":87350449,"serviceConfigId":"c7590100-94bd-4627-9401-08e30534dcb1","titleType":"DGame","platform":"Durango","name":"NieR:Automata\u2122 BECOME AS GODS Edition","earnedAchievements":7,"currentGamerscore":105,"maxGamerscore":1000},{"lastUnlock":"2016-05-01T08:47:34.0430627Z","titleId":89165390,"serviceConfigId":"faa90100-64d2-4520-bccf-790405508e4e","titleType":"DGame","platform":"Durango","name":"TRON RUN\/r","earnedAchievements":3,"currentGamerscore":100,"maxGamerscore":1250},{"lastUnlock":"2018-04-28T10:22:25.1230000Z","titleId":93901068,"serviceConfigId":"eced0100-ed11-4094-af25-077b0598d10c","titleType":"DGame","platform":"Durango","name":"Ruiner","earnedAchievements":5,"currentGamerscore":115,"maxGamerscore":1500},{"lastUnlock":"2017-03-06T18:29:42.0570000Z","titleId":112474113,"serviceConfigId":"74990100-fa46-44ac-8229-ffc006b43801","titleType":"Game","platform":"XboxOne","name":"Toby: The Secret Mine","earnedAchievements":10,"currentGamerscore":1000,"maxGamerscore":1000},{"lastUnlock":"2016-12-27T20:53:05.5640000Z","titleId":122001257,"serviceConfigId":"64c10100-3d40-49d5-8f1c-c99807459769","titleType":"LiveApp","platform":"Durango","name":"YouTube","earnedAchievements":9,"currentGamerscore":0,"maxGamerscore":0},{"lastUnlock":"2017-03-26T07:56:17.9600000Z","titleId":145718352,"serviceConfigId":"dcd80100-58ec-468d-92d5-a3a908af7c50","titleType":"Game","platform":"XboxOne","name":"Stardust Galaxy Warriors: Stellar Climax","earnedAchievements":1,"currentGamerscore":10,"maxGamerscore":1165},{"lastUnlock":"2017-02-10T18:57:59.9990000Z","titleId":155427331,"serviceConfigId":"5e900100-ec9e-4770-ae89-a7bf0943a203","titleType":"Game","platform":"XboxOne","name":"8DAYS","earnedAchievements":1,"currentGamerscore":20,"maxGamerscore":1000},{"lastUnlock":"2015-12-16T08:38:19.0609427Z","titleId":156829627,"serviceConfigId":"5fcb0100-fc74-4e4e-bff4-17c7095907bb","titleType":"Game","platform":"XboxOne","name":"No Time To Explain","earnedAchievements":1,"currentGamerscore":25,"maxGamerscore":1000},{"lastUnlock":"2017-03-18T19:05:47.7130000Z","titleId":157973080,"serviceConfigId":"01570100-f15b-4c96-ad9f-9b69096a7a58","titleType":"DGame","platform":"Durango","name":"NeuroVoider","earnedAchievements":3,"currentGamerscore":30,"maxGamerscore":1000},{"lastUnlock":"2017-02-02T19:24:20.4970000Z","titleId":164052911,"serviceConfigId":"86510100-4988-402c-9b99-b28f09c73faf","titleType":"Game","platform":"XboxOne","name":"Coffin Dodgers","earnedAchievements":6,"currentGamerscore":105,"maxGamerscore":1000},{"lastUnlock":"2017-11-18T16:24:55.0900000Z","titleId":164348348,"serviceConfigId":"2acf0100-c8d8-4d4b-bc20-1b4a09cbc1bc","titleType":"Game","platform":"XboxOne","name":"Tokyo 42","earnedAchievements":1,"currentGamerscore":10,"maxGamerscore":1000},{"lastUnlock":"2016-03-12T20:48:54.4890512Z","titleId":170095691,"serviceConfigId":"e1a40100-2c26-4fc8-acbd-da350a23744b","titleType":"Game","platform":"XboxOne","name":"Nightmares from the Deep: The Cursed Heart","earnedAchievements":9,"currentGamerscore":550,"maxGamerscore":1000},{"lastUnlock":"2017-01-02T18:16:03.7610000Z","titleId":181110324,"serviceConfigId":"10d30100-50cc-4439-b6b0-ec600acb8634","titleType":"Game","platform":"XboxOne","name":"The Bunker","earnedAchievements":20,"currentGamerscore":580,"maxGamerscore":1000},{"lastUnlock":"2018-06-17T15:33:47.0310000Z","titleId":184042097,"serviceConfigId":"e4600100-401b-4bd0-b8db-e2180af84271","titleType":"DGame","platform":"Durango","name":"Fe","earnedAchievements":2,"currentGamerscore":100,"maxGamerscore":1000},{"lastUnlock":"2017-08-01T18:07:22.3350000Z","titleId":188783392,"serviceConfigId":"86c60100-538e-4a4a-ba89-283e0b409b20","titleType":"Game","platform":"XboxOne","name":"Cobalt","earnedAchievements":3,"currentGamerscore":30,"maxGamerscore":1000},{"lastUnlock":"2018-10-22T16:54:31.0700000Z","titleId":188910190,"serviceConfigId":"77700100-1dbb-425b-b508-44b50b428a6e","titleType":"Game","platform":"XboxOne","name":"Tesla vs Lovecraft","earnedAchievements":5,"currentGamerscore":250,"maxGamerscore":1000},{"lastUnlock":"2017-02-18T12:15:28.6100000Z","titleId":208741763,"serviceConfigId":"81070100-4b70-4743-8158-22c20c712583","titleType":"DGame","platform":"Durango","name":"Subject 13","earnedAchievements":3,"currentGamerscore":180,"maxGamerscore":1000},{"lastUnlock":"2016-04-30T09:44:57.7323858Z","titleId":211501762,"serviceConfigId":"7c0b0100-36bb-4d92-a353-d5d60c9b42c2","titleType":"Game","platform":"XboxOne","name":"Beatbuddy: Tale of the Guardians","earnedAchievements":5,"currentGamerscore":200,"maxGamerscore":1000},{"lastUnlock":"2017-06-30T16:13:32.3630000Z","titleId":212246852,"serviceConfigId":"992e0100-bffa-48cc-971c-ce3f0ca6a144","titleType":"Game","platform":"XboxOne","name":"Furi","earnedAchievements":2,"currentGamerscore":30,"maxGamerscore":1000},{"lastUnlock":"2018-05-12T16:20:24.8730000Z","titleId":217802058,"serviceConfigId":"09a00100-0b9f-4ed6-a372-90960cfb654a","titleType":"Game","platform":"XboxOne","name":"Darkest Dungeon\u00ae","earnedAchievements":41,"currentGamerscore":675,"maxGamerscore":1305},{"lastUnlock":"2017-02-22T17:23:00.3800000Z","titleId":218721783,"serviceConfigId":"40180100-6348-4b25-b748-1bd60d096df7","titleType":"Game","platform":"XboxOne","name":"Feist","earnedAchievements":3,"currentGamerscore":45,"maxGamerscore":1000},{"lastUnlock":"2016-09-26T16:30:15.8045250Z","titleId":227108897,"serviceConfigId":"19020100-16e6-41b2-9e1e-095c0d896821","titleType":"DGame","platform":"Durango","name":"Virginia","earnedAchievements":6,"currentGamerscore":320,"maxGamerscore":1000},{"lastUnlock":"2017-06-21T16:33:16.5980000Z","titleId":229669525,"serviceConfigId":"ccd70100-dbfb-4c53-8e6e-d06f0db07a95","titleType":"Game","platform":"XboxOne","name":"Heart&Slash","earnedAchievements":2,"currentGamerscore":40,"maxGamerscore":1000},{"lastUnlock":"2018-09-11T08:23:47.9450000Z","titleId":232457702,"serviceConfigId":"e5220100-4160-43cc-8cb3-86570ddb05e6","titleType":"DGame","platform":"Durango","name":"Broken Age","earnedAchievements":30,"currentGamerscore":570,"maxGamerscore":1000},{"lastUnlock":"2017-07-23T17:55:03.8890000Z","titleId":240091546,"serviceConfigId":"f2220100-f81b-411c-8d12-4e7c0e4f819a","titleType":"Game","platform":"XboxOne","name":"SUPERHOT","earnedAchievements":8,"currentGamerscore":190,"maxGamerscore":1000},{"lastUnlock":"2017-12-02T10:22:54.6520000Z","titleId":244792213,"serviceConfigId":"5cf60100-0c1c-46ef-8033-f8730e973b95","titleType":"Game","platform":"XboxOne","name":"Morphite","earnedAchievements":1,"currentGamerscore":20,"maxGamerscore":1000},{"lastUnlock":"2019-01-10T20:23:11.5700000Z","titleId":245236582,"serviceConfigId":"83c50100-e65d-41e9-92d4-37c30e9e0366","titleType":"Game","platform":"XboxOne","name":"Celeste","earnedAchievements":3,"currentGamerscore":65,"maxGamerscore":1000},{"lastUnlock":"2016-01-03T17:07:38.0912319Z","titleId":247124088,"serviceConfigId":"ef740100-b381-4b17-b577-f06d0ebad078","titleType":"Game","platform":"XboxOne","name":"Shovel Knight: Treasure Trove","earnedAchievements":1,"currentGamerscore":0,"maxGamerscore":2000},{"lastUnlock":"2015-08-30T18:50:18.0071328Z","titleId":247546985,"serviceConfigId":"37770100-f9ae-4b80-9dad-7c1d0ec14469","titleType":"DGame","platform":"Durango","name":"Destiny","earnedAchievements":12,"currentGamerscore":240,"maxGamerscore":1500},{"lastUnlock":"2017-03-04T17:50:37.0060000Z","titleId":247774493,"serviceConfigId":"eae60100-1560-4e62-9a31-a2fd0ec4bd1d","titleType":"Game","platform":"XboxOne","name":"The Incredible Adventures of Van Helsing","earnedAchievements":5,"currentGamerscore":100,"maxGamerscore":1000},{"lastUnlock":"2019-01-26T19:23:15.9170000Z","titleId":263319091,"serviceConfigId":"6acf0100-3d35-41b8-9cfe-a7820fb1ee33","titleType":"Game","platform":"XboxOne","name":"Knock-Knock","earnedAchievements":1,"currentGamerscore":55,"maxGamerscore":1000},{"lastUnlock":"2016-01-03T13:42:20.0142510Z","titleId":264259050,"serviceConfigId":"96430100-71ae-4488-8791-79d50fc045ea","titleType":"DGame","platform":"Durango","name":"Ori and the Blind Forest","earnedAchievements":33,"currentGamerscore":725,"maxGamerscore":1000},{"lastUnlock":"2019-02-04T17:28:49.5210000Z","titleId":282721798,"serviceConfigId":"5a5e0100-e0b2-4bb6-b9c9-07b510d9fe06","titleType":"Game","platform":"XboxOne","name":"Screencheat","earnedAchievements":2,"currentGamerscore":50,"maxGamerscore":1000},{"lastUnlock":"2018-03-31T07:23:45.3200000Z","titleId":288915516,"serviceConfigId":"09ad0100-70f2-4503-ad8a-cbde1138803c","titleType":"DGame","platform":"Durango","name":"Skyforge","earnedAchievements":3,"currentGamerscore":35,"maxGamerscore":1040},{"lastUnlock":"2016-09-24T17:20:52.9765952Z","titleId":303403679,"serviceConfigId":"33310100-f98a-4913-ae79-c51e1215929f","titleType":"Game","platform":"XboxOne","name":"Eventide: Slavic Fable","earnedAchievements":8,"currentGamerscore":145,"maxGamerscore":1000},{"lastUnlock":"2017-08-06T18:59:35.6650000Z","titleId":303740234,"serviceConfigId":"5ef10100-c2dc-44fc-bd37-f892121ab54a","titleType":"Game","platform":"XboxOne","name":"Oh...Sir! The Insult Simulator","earnedAchievements":3,"currentGamerscore":200,"maxGamerscore":1000},{"lastUnlock":"2016-07-27T16:51:46.1978245Z","titleId":310521611,"serviceConfigId":"b5770100-83a9-44d8-8eb2-9ec912822f0b","titleType":"Game","platform":"XboxOne","name":"Cast of the Seven Godsends - Redux","earnedAchievements":2,"currentGamerscore":2,"maxGamerscore":1000},{"lastUnlock":"2018-11-06T20:27:01.8070000Z","titleId":311085527,"serviceConfigId":"690f0100-d13f-487e-85a3-29a5128ac9d7","titleType":"Game","platform":"XboxOne","name":"Brawlout","earnedAchievements":2,"currentGamerscore":40,"maxGamerscore":1000},{"lastUnlock":"2016-10-16T08:45:07.8896102Z","titleId":322450727,"serviceConfigId":"b8bc0100-e383-4cee-a390-afcc13383527","titleType":"Game","platform":"XboxOne","name":"Rogue Legacy","earnedAchievements":3,"currentGamerscore":25,"maxGamerscore":1000},{"lastUnlock":"2016-04-14T16:46:31.5004071Z","titleId":325295891,"serviceConfigId":"36520100-48a4-4768-85be-053213639f13","titleType":"DGame","platform":"Durango","name":"Steredenn","earnedAchievements":7,"currentGamerscore":200,"maxGamerscore":1000},{"lastUnlock":"2016-01-31T13:16:41.5184456Z","titleId":327370029,"serviceConfigId":"595c0100-e535-40c1-93f6-a1b11383452d","titleType":"LiveApp","platform":"Durango","name":"Netflix","earnedAchievements":2,"currentGamerscore":0,"maxGamerscore":0},{"lastUnlock":"2018-12-03T19:54:54.6230000Z","titleId":332913499,"serviceConfigId":"77fb0100-6317-4b15-9b3a-d8df13d7db5b","titleType":"DGame","platform":"Durango","name":"Fallout 76","earnedAchievements":14,"currentGamerscore":200,"maxGamerscore":1000},{"lastUnlock":"2017-11-18T16:10:08.8260000Z","titleId":333628240,"serviceConfigId":"636a0100-392d-4116-9c4f-e0c513e2c350","titleType":"Game","platform":"XboxOne","name":"Quantum Break","earnedAchievements":3,"currentGamerscore":70,"maxGamerscore":1000},{"lastUnlock":"2018-08-18T19:55:19.6410000Z","titleId":340920273,"serviceConfigId":"bddf0100-1eee-4776-baa2-8123145207d1","titleType":"DGame","platform":"Durango","name":"Overcooked","earnedAchievements":7,"currentGamerscore":351,"maxGamerscore":1000},{"lastUnlock":"2019-02-04T19:58:48.7800000Z","titleId":341719186,"serviceConfigId":"fa210100-9a8a-49b1-92fa-4526145e3892","titleType":"Game","platform":"XboxOne","name":"Guns, Gore and Cannoli 2","earnedAchievements":8,"currentGamerscore":350,"maxGamerscore":1000},{"lastUnlock":"2017-07-20T18:20:27.0920000Z","titleId":364252200,"serviceConfigId":"c2340100-76ff-4b39-81c0-6c3f15b60c28","titleType":"Game","platform":"XboxOne","name":"Broken Sword 5 - the Serpent\u2019s Curse","earnedAchievements":28,"currentGamerscore":750,"maxGamerscore":1000},{"lastUnlock":"2017-11-07T19:27:46.3710000Z","titleId":386160977,"serviceConfigId":"49480100-803b-450f-b52b-51a817045951","titleType":"Game","platform":"XboxOne","name":"Zombie Vikings","earnedAchievements":4,"currentGamerscore":60,"maxGamerscore":1000},{"lastUnlock":"2018-11-08T19:16:06.4430000Z","titleId":394654741,"serviceConfigId":"d3960100-603b-4bba-9483-e91c1785f415","titleType":"Game","platform":"XboxOne","name":"GoNNER - BL\u00fcEBERRY EDiTION","earnedAchievements":3,"currentGamerscore":45,"maxGamerscore":1000},{"lastUnlock":"2017-04-06T18:26:24.5370000Z","titleId":401515813,"serviceConfigId":"6e400100-6c4b-4626-abe6-631f17eea525","titleType":"DGame","platform":"Durango","name":"Enter the Gungeon","earnedAchievements":1,"currentGamerscore":15,"maxGamerscore":1250},{"lastUnlock":"2018-09-19T20:21:02.0000000Z","titleId":410266496,"serviceConfigId":"f9030100-685e-4351-89ff-0ee218742b80","titleType":"DGame","platform":"Durango","name":"Monster Slayers","earnedAchievements":2,"currentGamerscore":25,"maxGamerscore":1000},{"lastUnlock":"2015-06-18T13:58:43.9671941Z","titleId":433988710,"serviceConfigId":"e37a0100-23cb-44bc-84fa-2e3b19de2466","titleType":"DGame","platform":"Durango","name":"MASSIVE CHALICE","earnedAchievements":6,"currentGamerscore":70,"maxGamerscore":1000},{"lastUnlock":"2016-04-28T13:45:44.4382184Z","titleId":438873974,"serviceConfigId":"69870100-172d-4c83-8896-d62b1a28af76","titleType":"Game","platform":"XboxOne","name":"Enigmatis: The Ghosts of Maple Creek","earnedAchievements":3,"currentGamerscore":175,"maxGamerscore":1000},{"lastUnlock":"2018-08-20T14:41:26.0140000Z","titleId":453395486,"serviceConfigId":"1e560100-1a93-4a04-b327-5dfd1b06441e","titleType":"Game","platform":"XboxOne","name":"Ultimate Chicken Horse","earnedAchievements":2,"currentGamerscore":50,"maxGamerscore":1000},{"lastUnlock":"2018-12-08T17:17:16.4270000Z","titleId":453783733,"serviceConfigId":"46df0100-a8cd-4d96-973f-b42a1b0c30b5","titleType":"Game","platform":"XboxOne","name":"Q.U.B.E. 2","earnedAchievements":5,"currentGamerscore":175,"maxGamerscore":1000},{"lastUnlock":"2017-01-16T18:25:59.4230000Z","titleId":460630685,"serviceConfigId":"04ee0100-83aa-417c-9815-0da41b74aa9d","titleType":"Game","platform":"XboxOne","name":"Rise & Shine","earnedAchievements":4,"currentGamerscore":325,"maxGamerscore":1000},{"lastUnlock":"2018-04-20T16:25:20.9830000Z","titleId":461678894,"serviceConfigId":"92a50100-43c7-4b43-a7f5-87b31b84a92e","titleType":"Game","platform":"XboxOne","name":"Owlboy","earnedAchievements":2,"currentGamerscore":10,"maxGamerscore":1000},{"lastUnlock":"2017-04-23T10:52:00.7040000Z","titleId":464969042,"serviceConfigId":"f8830100-ed51-48f6-8a08-b09e1bb6dd52","titleType":"Game","platform":"XboxOne","name":"The Solus Project","earnedAchievements":13,"currentGamerscore":299,"maxGamerscore":1000},{"lastUnlock":"2018-09-10T08:13:03.5990000Z","titleId":465259992,"serviceConfigId":"b9960100-efe5-46d3-b913-678f1bbb4dd8","titleType":"DGame","platform":"Durango","name":"Battle Chasers: Nightwar","earnedAchievements":1,"currentGamerscore":10,"maxGamerscore":1000},{"lastUnlock":"2018-11-11T17:39:03.0360000Z","titleId":465264365,"serviceConfigId":"c5fe0100-432f-4960-b195-6e8c1bbb5eed","titleType":"Game","platform":"XboxOne","name":"Way of the Passive Fist","earnedAchievements":1,"currentGamerscore":10,"maxGamerscore":1000},{"lastUnlock":"2019-02-11T18:04:28.8330000Z","titleId":469396406,"serviceConfigId":"e1930100-5ea7-4661-b4c9-d5331bfa6bb6","titleType":"Game","platform":"XboxOne","name":"Airheart - Tales of broken Wings","earnedAchievements":3,"currentGamerscore":75,"maxGamerscore":1000},{"lastUnlock":"2019-02-10T15:42:03.4500000Z","titleId":474102727,"serviceConfigId":"de600100-dd33-40ee-b97f-fbaf1c423bc7","titleType":"DGame","platform":"Durango","name":"Omega Strike","earnedAchievements":15,"currentGamerscore":385,"maxGamerscore":1000},{"lastUnlock":"2018-01-02T10:13:06.7630000Z","titleId":484274489,"serviceConfigId":"85140100-4ff6-42bd-aea2-604c1cdd7139","titleType":"Game","platform":"XboxOne","name":"Hammerwatch","earnedAchievements":5,"currentGamerscore":35,"maxGamerscore":1000},{"lastUnlock":"2019-01-06T18:42:31.7300000Z","titleId":497019090,"serviceConfigId":"f5d80100-1b7d-47e9-8b3b-2ef51d9fe8d2","titleType":"Game","platform":"XboxOne","name":"Chasm","earnedAchievements":4,"currentGamerscore":80,"maxGamerscore":1000},{"lastUnlock":"2016-10-09T12:16:51.7550764Z","titleId":498017453,"serviceConfigId":"5d910100-db55-4309-8ce4-d98a1daf24ad","titleType":"Game","platform":"XboxOne","name":"HoPiKo","earnedAchievements":3,"currentGamerscore":150,"maxGamerscore":1000},{"lastUnlock":"2017-12-20T16:01:43.0770000Z","titleId":498206038,"serviceConfigId":"c6300100-ff37-442c-9f27-6a771db20556","titleType":"DGame","platform":"Durango","name":"#KILLALLZOMBIES","earnedAchievements":4,"currentGamerscore":125,"maxGamerscore":1000},{"lastUnlock":"2017-06-25T16:56:45.1380000Z","titleId":517216795,"serviceConfigId":"36b70100-972c-4538-85be-e1601ed41a1b","titleType":"Game","platform":"XboxOne","name":"Quest of Dungeons","earnedAchievements":4,"currentGamerscore":110,"maxGamerscore":1000},{"lastUnlock":"2017-12-02T09:57:35.0650000Z","titleId":519443170,"serviceConfigId":"e1820100-4c4b-45de-8745-ff431ef612e2","titleType":"DGame","platform":"Durango","name":"Torment: Tides of Numenera","earnedAchievements":1,"currentGamerscore":30,"maxGamerscore":1000},{"lastUnlock":"2016-06-22T14:27:01.5142496Z","titleId":522988823,"serviceConfigId":"24a90100-a479-46e8-88ab-e30b1f2c2d17","titleType":"DGame","platform":"Durango","name":"LA Cops","earnedAchievements":2,"currentGamerscore":150,"maxGamerscore":1000},{"lastUnlock":"2019-01-12T10:06:22.3330000Z","titleId":523071548,"serviceConfigId":"27830100-4d45-414e-8c09-9e4e1f2d703c","titleType":"DGame","platform":"Durango","name":"Rad Rodgers","earnedAchievements":4,"currentGamerscore":50,"maxGamerscore":1000},{"lastUnlock":"2015-05-03T14:10:19.2886404Z","titleId":524641908,"serviceConfigId":"9a7f0100-0d4e-4f2f-af47-98d61f456674","titleType":"DGame","platform":"Durango","name":"Assassin's Creed\u00ae Chronicles: China","earnedAchievements":1,"currentGamerscore":25,"maxGamerscore":1000},{"lastUnlock":"2017-12-29T16:41:38.2680000Z","titleId":528264958,"serviceConfigId":"3aa00100-ed92-4fd9-ad08-d7d91f7caefe","titleType":"DGame","platform":"Durango","name":"Sine Mora EX","earnedAchievements":1,"currentGamerscore":50,"maxGamerscore":1000},{"lastUnlock":"2018-12-01T15:30:37.5300000Z","titleId":531022146,"serviceConfigId":"a4b00100-8b68-48f5-a740-76ee1fa6c142","titleType":"Game","platform":"XboxOne","name":"AQUA KITTY UDX: Xbox One Ultra Edition","earnedAchievements":25,"currentGamerscore":440,"maxGamerscore":1000},{"lastUnlock":"2018-06-08T20:48:05.1570000Z","titleId":555542903,"serviceConfigId":"58ab0100-82fa-49ec-8a9c-835f211ce977","titleType":"DGame","platform":"Durango","name":"Yoku's Island Express","earnedAchievements":27,"currentGamerscore":880,"maxGamerscore":1000},{"lastUnlock":"2018-12-28T18:14:01.6200000Z","titleId":558797228,"serviceConfigId":"90c40100-9123-47d6-bc6b-35d3214e91ac","titleType":"DGame","platform":"Durango","name":"Rocket League\u00ae","earnedAchievements":45,"currentGamerscore":1130,"maxGamerscore":2200},{"lastUnlock":"2016-03-27T18:56:06.1948812Z","titleId":559544937,"serviceConfigId":"cf540100-ba15-40c8-a416-b6172159fa69","titleType":"DGame","platform":"Durango","name":"Ori and the Blind Forest: Definitive Edition","earnedAchievements":47,"currentGamerscore":960,"maxGamerscore":1250},{"lastUnlock":"2017-03-12T20:33:48.3590000Z","titleId":570054502,"serviceConfigId":"6b6a0100-4359-4c1f-9054-88e421fa5766","titleType":"Game","platform":"XboxOne","name":"The Bug Butcher","earnedAchievements":3,"currentGamerscore":100,"maxGamerscore":1000},{"lastUnlock":"2017-11-19T16:08:10.4190000Z","titleId":572268056,"serviceConfigId":"00520100-2610-4705-8633-3c41221c1e18","titleType":"DGame","platform":"Durango","name":"Little Nightmares","earnedAchievements":1,"currentGamerscore":50,"maxGamerscore":2200},{"lastUnlock":"2017-02-10T20:52:33.1770000Z","titleId":592146950,"serviceConfigId":"1e670100-9a45-4953-b898-1b9a234b7206","titleType":"DGame","platform":"Durango","name":"Adventure Pop","earnedAchievements":6,"currentGamerscore":200,"maxGamerscore":1000},{"lastUnlock":"2018-09-12T17:09:23.1140000Z","titleId":594585699,"serviceConfigId":"75fd0100-155e-49fd-abc5-67ee2370a863","titleType":"Game","platform":"XboxOne","name":"Nidhogg 2","earnedAchievements":4,"currentGamerscore":225,"maxGamerscore":1000},{"lastUnlock":"2016-01-11T19:50:37.1051832Z","titleId":597771444,"serviceConfigId":"ed190100-58a8-4dd8-8019-8e8323a144b4","titleType":"DGame","platform":"Durango","name":"Gems of War","earnedAchievements":7,"currentGamerscore":140,"maxGamerscore":2350},{"lastUnlock":"2018-12-16T18:30:19.4710000Z","titleId":601877820,"serviceConfigId":"67dd0100-8d07-42f4-a49b-6d4723dfed3c","titleType":"DGame","platform":"Durango","name":"Yesterday Origins","earnedAchievements":3,"currentGamerscore":60,"maxGamerscore":1000},{"lastUnlock":"2019-02-19T17:53:49.8940000Z","titleId":606152324,"serviceConfigId":"8ab00100-4272-4e9d-9753-467624212684","titleType":"DGame","platform":"Durango","name":"GWENT: The Witcher Card Game","earnedAchievements":1,"currentGamerscore":15,"maxGamerscore":1000},{"lastUnlock":"2016-06-19T20:31:36.4870259Z","titleId":617479290,"serviceConfigId":"c1730100-b9a6-47d8-a904-123c24cdfc7a","titleType":"Game","platform":"XboxOne","name":"Neon Chrome","earnedAchievements":2,"currentGamerscore":100,"maxGamerscore":1000},{"lastUnlock":"2018-08-18T17:17:42.5930000Z","titleId":623325843,"serviceConfigId":"07340100-90e7-4da5-8ca0-e0d225273293","titleType":"DGame","platform":"Durango","name":"Cuphead","earnedAchievements":9,"currentGamerscore":215,"maxGamerscore":1000},{"lastUnlock":"2017-04-20T20:14:08.9930000Z","titleId":631368453,"serviceConfigId":"1f220100-7855-4cb7-b11e-6b2625a1eb05","titleType":"DGame","platform":"Durango","name":"Necropolis","earnedAchievements":6,"currentGamerscore":300,"maxGamerscore":1000},{"lastUnlock":"2016-08-06T16:39:47.4010000Z","titleId":649279273,"serviceConfigId":"98a50100-fb08-4b3a-a6f5-6b8426b33729","titleType":"DGame","platform":"Durango","name":"King's Quest\u2122","earnedAchievements":4,"currentGamerscore":265,"maxGamerscore":1800},{"lastUnlock":"2017-04-09T10:42:05.9890000Z","titleId":653726544,"serviceConfigId":"803c0100-3c7d-4b84-9be8-d17526f71350","titleType":"Game","platform":"XboxOne","name":"Toy Odyssey","earnedAchievements":4,"currentGamerscore":120,"maxGamerscore":1000},{"lastUnlock":"2015-03-13T11:55:42.1020724Z","titleId":666757656,"serviceConfigId":"eb970100-1ba4-4575-9fe1-13c827bdea18","titleType":"DGame","platform":"Durango","name":"Rayman Legends","earnedAchievements":7,"currentGamerscore":70,"maxGamerscore":1000},{"lastUnlock":"2016-09-10T07:04:17.5120000Z","titleId":667003203,"serviceConfigId":"43770100-62a5-44d6-b495-2d0027c1a943","titleType":"Game","platform":"XboxOne","name":"Dogos","earnedAchievements":1,"currentGamerscore":30,"maxGamerscore":1000},{"lastUnlock":"2018-12-28T15:01:03.1630000Z","titleId":687339341,"serviceConfigId":"99c40100-2fed-45c6-bd56-4ea928f7f74d","titleType":"DGame","platform":"Durango","name":"Brawlhalla","earnedAchievements":2,"currentGamerscore":30,"maxGamerscore":1000},{"lastUnlock":"2018-09-10T08:54:13.7900000Z","titleId":693104257,"serviceConfigId":"04050100-8264-4d88-8f24-c359294fee81","titleType":"Game","platform":"XboxOne","name":"The Station","earnedAchievements":1,"currentGamerscore":75,"maxGamerscore":1000},{"lastUnlock":"2018-10-07T17:48:26.9070000Z","titleId":702883504,"serviceConfigId":"e91e0100-3a16-47a9-9c38-dc2c29e526b0","titleType":"Game","platform":"XboxOne","name":"The Long Reach","earnedAchievements":1,"currentGamerscore":50,"maxGamerscore":1000},{"lastUnlock":"2018-03-13T20:28:02.7370000Z","titleId":706918470,"serviceConfigId":"bdcf0100-a2ef-4c58-9b7e-09532a22b846","titleType":"Game","platform":"XboxOne","name":"Crimsonland","earnedAchievements":12,"currentGamerscore":360,"maxGamerscore":1000},{"lastUnlock":"2017-01-01T21:12:32.7580000Z","titleId":708889423,"serviceConfigId":"3a9e0100-d52f-40fd-bd30-87fd2a40cb4f","titleType":"DGame","platform":"Durango","name":"Slain: Back from Hell","earnedAchievements":3,"currentGamerscore":60,"maxGamerscore":1000},{"lastUnlock":"2016-08-15T17:21:47.7890000Z","titleId":720702755,"serviceConfigId":"36320100-4541-476c-9703-d47e2af50d23","titleType":"Game","platform":"XboxOne","name":"Hyper Light Drifter","earnedAchievements":11,"currentGamerscore":550,"maxGamerscore":1150},{"lastUnlock":"2017-01-22T16:04:07.3170000Z","titleId":722916288,"serviceConfigId":"10be0100-a3eb-45fa-aeb5-e9852b16d3c0","titleType":"Game","platform":"XboxOne","name":"Hue","earnedAchievements":12,"currentGamerscore":800,"maxGamerscore":1000},{"lastUnlock":"2017-05-07T18:36:17.0890000Z","titleId":725442241,"serviceConfigId":"c9ba0100-7d8b-4bad-83d3-be522b3d5ec1","titleType":"DGame","platform":"Durango","name":"Darksiders Warmastered Edition","earnedAchievements":20,"currentGamerscore":365,"maxGamerscore":1000},{"lastUnlock":"2018-05-21T10:29:27.9130000Z","titleId":754617166,"serviceConfigId":"85370100-b0e9-4afa-b9e9-51452cfa8b4e","titleType":"Game","platform":"XboxOne","name":"Subterrain","earnedAchievements":1,"currentGamerscore":10,"maxGamerscore":1000},{"lastUnlock":"2016-06-12T09:04:39.6165447Z","titleId":761852503,"serviceConfigId":"f0490100-f8af-4df2-be3e-87572d68f257","titleType":"Game","platform":"XboxOne","name":"Clockwork Tales: Of Glass and Ink","earnedAchievements":13,"currentGamerscore":520,"maxGamerscore":1000},{"lastUnlock":"2017-09-24T13:54:54.1870000Z","titleId":778803087,"serviceConfigId":"35640100-8d77-4384-9e03-a09e2e6b978f","titleType":"DGame","platform":"Durango","name":"Spacelords","earnedAchievements":1,"currentGamerscore":20,"maxGamerscore":1820},{"lastUnlock":"2017-09-24T12:39:33.3760000Z","titleId":779348826,"serviceConfigId":"5b800100-f26e-48e1-8403-f0a62e73eb5a","titleType":"DGame","platform":"Durango","name":"Livelock","earnedAchievements":11,"currentGamerscore":180,"maxGamerscore":1000},{"lastUnlock":"2019-01-08T21:23:29.9440000Z","titleId":794552001,"serviceConfigId":"13400100-a2c0-4962-824f-c7c92f5be6c1","titleType":"Game","platform":"XboxOne","name":"The Binding of Isaac: Rebirth","earnedAchievements":63,"currentGamerscore":1090,"maxGamerscore":1155},{"lastUnlock":"2016-10-15T08:04:59.0197939Z","titleId":798834281,"serviceConfigId":"91b20100-da0d-4937-a354-0dfc2f9d3e69","titleType":"Game","platform":"XboxOne","name":"Manual Samuel","earnedAchievements":15,"currentGamerscore":460,"maxGamerscore":1000},{"lastUnlock":"2018-08-27T16:42:18.3400000Z","titleId":810101074,"serviceConfigId":"1f2a0100-5366-49dd-b1ba-9f9b30492952","titleType":"Game","platform":"XboxOne","name":"Dead Cells","earnedAchievements":9,"currentGamerscore":110,"maxGamerscore":1000},{"lastUnlock":"2016-04-19T17:24:30.0578062Z","titleId":820078969,"serviceConfigId":"56ed0100-1d50-4e91-9a1a-911c30e16979","titleType":"Game","platform":"XboxOne","name":"Zombie Driver Ultimate Edition","earnedAchievements":1,"currentGamerscore":10,"maxGamerscore":2000},{"lastUnlock":"2017-02-18T17:49:18.7580000Z","titleId":830649354,"serviceConfigId":"b5fe0100-c634-4d68-870b-7bc83182b40a","titleType":"DGame","platform":"Durango","name":"Dying Light","earnedAchievements":47,"currentGamerscore":1120,"maxGamerscore":1490},{"lastUnlock":"2017-02-19T15:10:27.9890000Z","titleId":837159338,"serviceConfigId":"6ccf0100-f34a-45ca-862e-215d31e609aa","titleType":"Game","platform":"XboxOne","name":"Typoman","earnedAchievements":12,"currentGamerscore":500,"maxGamerscore":1000},{"lastUnlock":"2017-03-09T18:18:40.9910000Z","titleId":848645857,"serviceConfigId":"5c4f0100-e797-4633-a081-f44232954ee1","titleType":"DGame","platform":"Durango","name":"Vertical Drop Heroes HD","earnedAchievements":7,"currentGamerscore":450,"maxGamerscore":1000},{"lastUnlock":"2017-03-18T18:36:04.9590000Z","titleId":852431422,"serviceConfigId":"31ba0100-1d30-40c4-9816-9d6c32cf123e","titleType":"DGame","platform":"Durango","name":"ReCore: Definitive Edition","earnedAchievements":5,"currentGamerscore":110,"maxGamerscore":1500},{"lastUnlock":"2018-12-09T12:58:17.8400000Z","titleId":857446909,"serviceConfigId":"48e30100-58c0-4c35-9035-abda331b99fd","titleType":"Game","platform":"XboxOne","name":"Chaos on Deponia","earnedAchievements":1,"currentGamerscore":20,"maxGamerscore":1000},{"lastUnlock":"2018-09-26T16:54:20.2510000Z","titleId":858411141,"serviceConfigId":"ec1a0100-e9e3-4cab-932e-75dc332a5085","titleType":"Game","platform":"XboxOne","name":"Die for Valhalla!","earnedAchievements":18,"currentGamerscore":390,"maxGamerscore":1000},{"lastUnlock":"2018-04-29T10:46:09.2170000Z","titleId":859843286,"serviceConfigId":"e5110100-4f5a-4846-97cd-202e33402ad6","titleType":"Game","platform":"XboxOne","name":"Hellblade: Senua's Sacrifice","earnedAchievements":1,"currentGamerscore":90,"maxGamerscore":1000},{"lastUnlock":"2017-11-26T21:03:31.1020000Z","titleId":861949148,"serviceConfigId":"33fe0100-d4c9-4e30-a5ec-e89d33604cdc","titleType":"Game","platform":"XboxOne","name":"What Remains of Edith Finch","earnedAchievements":1,"currentGamerscore":100,"maxGamerscore":1000},{"lastUnlock":"2018-02-07T17:30:58.4980000Z","titleId":873887021,"serviceConfigId":"03750100-3bc6-4a8d-a05c-338e3416752d","titleType":"DGame","platform":"Durango","name":"Rogue Stormers","earnedAchievements":8,"currentGamerscore":100,"maxGamerscore":1000},{"lastUnlock":"2016-09-04T16:50:26.3530000Z","titleId":875174887,"serviceConfigId":"9e740100-a264-4078-b8f9-482e342a1be7","titleType":"Game","platform":"XboxOne","name":"The Final Station","earnedAchievements":1,"currentGamerscore":100,"maxGamerscore":2300},{"lastUnlock":"2016-07-30T10:18:24.8721083Z","titleId":885488152,"serviceConfigId":"61af0100-9a70-444f-9aeb-132234c77a18","titleType":"Game","platform":"XboxOne","name":"INSIDE","earnedAchievements":1,"currentGamerscore":70,"maxGamerscore":1000},{"lastUnlock":"2016-10-02T16:12:10.1050396Z","titleId":903716936,"serviceConfigId":"8fb20100-7871-49ed-8c4e-2d3435dda048","titleType":"Game","platform":"XboxOne","name":"Dear Esther: Landmark Edition","earnedAchievements":1,"currentGamerscore":50,"maxGamerscore":1000},{"lastUnlock":"2017-03-19T09:18:04.9450000Z","titleId":910593568,"serviceConfigId":"8b520100-3075-445d-99f1-aeef36468e20","titleType":"Game","platform":"XboxOne","name":"Never Alone (Kisima Ingitchuna)","earnedAchievements":3,"currentGamerscore":150,"maxGamerscore":1175},{"lastUnlock":"2017-05-20T16:39:22.6520000Z","titleId":912254227,"serviceConfigId":"e8c60100-1ef2-4496-8fec-f105365fe513","titleType":"Game","platform":"XboxOne","name":"Pit People","earnedAchievements":6,"currentGamerscore":325,"maxGamerscore":1500},{"lastUnlock":"2016-04-21T16:15:32.4535785Z","titleId":916339986,"serviceConfigId":"173c0100-cf9c-453c-9460-a096369e3d12","titleType":"Game","platform":"XboxOne","name":"Party Hard","earnedAchievements":2,"currentGamerscore":50,"maxGamerscore":1000},{"lastUnlock":"2016-08-21T11:31:25.8680000Z","titleId":928096970,"serviceConfigId":"b32e0100-8014-44fb-a4c5-eb943751a2ca","titleType":"DGame","platform":"Durango","name":"Happy Dungeons","earnedAchievements":1,"currentGamerscore":10,"maxGamerscore":1250},{"lastUnlock":"2018-10-07T11:52:26.5430000Z","titleId":940586683,"serviceConfigId":"6de90100-7410-4cca-9506-ef53381036bb","titleType":"Game","platform":"XboxOne","name":"Wizard of Legend","earnedAchievements":1,"currentGamerscore":20,"maxGamerscore":1000},{"lastUnlock":"2018-12-08T16:14:19.5650000Z","titleId":945909358,"serviceConfigId":"43c90100-1704-438e-b21f-e68a38616e6e","titleType":"Game","platform":"XboxOne","name":"Subnautica","earnedAchievements":3,"currentGamerscore":75,"maxGamerscore":1000},{"lastUnlock":"2015-06-18T12:33:38.8203485Z","titleId":946215144,"serviceConfigId":"14080100-0c11-436f-92a2-66b7386618e8","titleType":"DGame","platform":"Durango","name":"AirMech\u00ae Arena","earnedAchievements":1,"currentGamerscore":10,"maxGamerscore":1000},{"lastUnlock":"2018-09-10T08:41:52.7740000Z","titleId":1003504679,"serviceConfigId":"7bd60100-5afe-4a5b-a116-461d3bd04427","titleType":"Game","platform":"XboxOne","name":"Dead Age","earnedAchievements":1,"currentGamerscore":10,"maxGamerscore":1000},{"lastUnlock":"2017-01-03T15:54:12.4710000Z","titleId":1008687929,"serviceConfigId":"1a930100-429f-476c-bfaf-f01b3c1f5b39","titleType":"DGame","platform":"Durango","name":"Mortal Kombat X","earnedAchievements":18,"currentGamerscore":340,"maxGamerscore":1500},{"lastUnlock":"2018-12-16T17:18:41.7460000Z","titleId":1015340672,"serviceConfigId":"a3ab0100-75f1-4191-81ef-64573c84de80","titleType":"DGame","platform":"Durango","name":"Thimbleweed Park","earnedAchievements":29,"currentGamerscore":825,"maxGamerscore":1000},{"lastUnlock":"2016-01-01T07:56:29.5960520Z","titleId":1026512979,"serviceConfigId":"2b6c0100-f1d1-41fd-a739-7c833d2f5853","titleType":"DGame","platform":"Durango","name":"How to Survive: Storm Warning Edition","earnedAchievements":1,"currentGamerscore":15,"maxGamerscore":1000},{"lastUnlock":"2015-01-03T17:48:59.0182820Z","titleId":1033012343,"serviceConfigId":"2f4e194d-16b5-47c3-b7e8-ec284282a67a","titleType":"DGame","platform":"Durango","name":"D4: Dark Dreams Don't Die","earnedAchievements":9,"currentGamerscore":65,"maxGamerscore":1000},{"lastUnlock":"2017-11-05T16:33:33.9020000Z","titleId":1045880316,"serviceConfigId":"95320100-0634-42ca-80c9-61e43e56ddfc","titleType":"Game","platform":"XboxOne","name":"Bulb Boy","earnedAchievements":8,"currentGamerscore":600,"maxGamerscore":1000},{"lastUnlock":"2016-05-07T11:58:35.6077863Z","titleId":1049928193,"serviceConfigId":"05740100-2524-4613-b165-d05b3e94a201","titleType":"Game","platform":"XboxOne","name":"Azkend 2: The World Beneath","earnedAchievements":1,"currentGamerscore":25,"maxGamerscore":1000},{"lastUnlock":"2016-08-21T11:19:31.6020000Z","titleId":1055556936,"serviceConfigId":"421c0100-054a-4958-b20c-8b9b3eea8548","titleType":"Game","platform":"XboxOne","name":"Kingdom: New Lands","earnedAchievements":1,"currentGamerscore":20,"maxGamerscore":1000},{"lastUnlock":"2017-04-08T09:00:12.4590000Z","titleId":1066906675,"serviceConfigId":"36850100-6abe-4b28-ac5d-d9493f97b433","titleType":"DGame","platform":"Durango","name":"Vikings - Wolves of Midgard","earnedAchievements":1,"currentGamerscore":15,"maxGamerscore":1000},{"lastUnlock":"2016-05-22T13:00:27.6482804Z","titleId":1090851408,"serviceConfigId":"3eed0100-ab96-4cfb-8ba1-44b341051250","titleType":"DGame","platform":"Durango","name":"TEMBO THE BADASS ELEPHANT","earnedAchievements":2,"currentGamerscore":60,"maxGamerscore":1000},{"lastUnlock":"2016-03-05T09:29:38.2020240Z","titleId":1131124715,"serviceConfigId":"3df70100-24d3-438f-a69d-34f3436b97eb","titleType":"Game","platform":"XboxOne","name":"Guns, Gore and Cannoli","earnedAchievements":13,"currentGamerscore":600,"maxGamerscore":1000},{"lastUnlock":"2018-03-31T12:03:33.9930000Z","titleId":1145574011,"serviceConfigId":"387a0100-dd3f-4dd2-9471-88134448127b","titleType":"DGame","platform":"Durango","name":"Titanfall\u2122 2","earnedAchievements":3,"currentGamerscore":60,"maxGamerscore":1000},{"lastUnlock":"2016-10-15T09:39:23.7128781Z","titleId":1152151422,"serviceConfigId":"9a8f0100-1917-4881-a723-ce0e44ac6f7e","titleType":"Game","platform":"XboxOne","name":"BADLAND: Game of the Year Edition","earnedAchievements":10,"currentGamerscore":100,"maxGamerscore":1000},{"lastUnlock":"2017-03-12T17:41:03.0480000Z","titleId":1161955801,"serviceConfigId":"00340100-9596-4613-80ab-2838454209d9","titleType":"DGame","platform":"Durango","name":"The Technomancer","earnedAchievements":8,"currentGamerscore":115,"maxGamerscore":1000},{"lastUnlock":"2017-01-02T18:57:31.5450000Z","titleId":1175562227,"serviceConfigId":"de480100-8417-4199-91fe-b2a84611a7f3","titleType":"DGame","platform":"Durango","name":"Just Cause 3","earnedAchievements":2,"currentGamerscore":20,"maxGamerscore":1605},{"lastUnlock":"2019-01-27T06:14:14.9890000Z","titleId":1204533074,"serviceConfigId":"61140100-beed-4771-9804-3d6747cbb752","titleType":"DGame","platform":"Durango","name":"Borderlands 2","earnedAchievements":52,"currentGamerscore":1160,"maxGamerscore":1625},{"lastUnlock":"2016-06-25T11:30:13.1237052Z","titleId":1246613109,"serviceConfigId":"04db0100-0878-4620-afba-96984a4dce75","titleType":"DGame","platform":"Durango","name":"Borderlands: The Pre-Sequel","earnedAchievements":44,"currentGamerscore":915,"maxGamerscore":1370},{"lastUnlock":"2015-11-22T19:15:33.1584990Z","titleId":1271641024,"serviceConfigId":"25cb0100-004a-4fca-9369-496b4bcbb3c0","titleType":"DGame","platform":"Durango","name":"Lords of the Fallen","earnedAchievements":4,"currentGamerscore":60,"maxGamerscore":1200},{"lastUnlock":"2016-06-05T11:50:14.1866438Z","titleId":1278934710,"serviceConfigId":"dc780100-f177-4845-aadc-445c4c3afeb6","titleType":"Game","platform":"XboxOne","name":"Albedo: Eyes From Outer Space","earnedAchievements":1,"currentGamerscore":30,"maxGamerscore":1000},{"lastUnlock":"2014-11-02T12:40:04.1300529Z","titleId":1285127818,"serviceConfigId":"eabb0100-ffce-45be-859d-7c7f4c997e8a","titleType":"Game","platform":"XboxOne","name":"Chariot","earnedAchievements":3,"currentGamerscore":30,"maxGamerscore":1200},{"lastUnlock":"2016-04-17T16:48:20.4982556Z","titleId":1292135256,"serviceConfigId":"7d0597d8-2113-423a-9e4f-ed725b9d43ba","titleType":"DGame","platform":"Durango","name":"Titanfall","earnedAchievements":1,"currentGamerscore":25,"maxGamerscore":2000},{"lastUnlock":"2016-09-24T18:23:35.2681474Z","titleId":1307429766,"serviceConfigId":"d4340100-0d67-48a1-93a2-a3834dedcb86","titleType":"DGame","platform":"Durango","name":"Worms Battlegrounds","earnedAchievements":1,"currentGamerscore":20,"maxGamerscore":1250},{"lastUnlock":"2016-11-28T16:58:22.9200000Z","titleId":1327376519,"serviceConfigId":"5c5b0100-69c4-40bd-8971-ba0f4f1e2887","titleType":"DGame","platform":"Durango","name":"DOOM","earnedAchievements":9,"currentGamerscore":200,"maxGamerscore":1580},{"lastUnlock":"2016-10-31T12:23:46.5898791Z","titleId":1328778537,"serviceConfigId":"63c20100-5668-4d72-930c-ac714f338d29","titleType":"Game","platform":"XboxOne","name":"SteamWorld Dig","earnedAchievements":1,"currentGamerscore":50,"maxGamerscore":1000},{"lastUnlock":"2016-05-01T14:05:39.4463831Z","titleId":1339178390,"serviceConfigId":"cfa20100-f5ba-4ebd-8f93-26954fd23d96","titleType":"DGame","platform":"Durango","name":"White Night","earnedAchievements":20,"currentGamerscore":470,"maxGamerscore":1000},{"lastUnlock":"2014-12-19T15:46:26.8294843Z","titleId":1367952835,"serviceConfigId":"1f990100-8da6-404f-9837-8f8151894dc3","titleType":"DGame","platform":"Durango","name":"Far Cry\u00ae 4","earnedAchievements":4,"currentGamerscore":60,"maxGamerscore":1250},{"lastUnlock":"2017-03-19T06:40:30.2060000Z","titleId":1375399089,"serviceConfigId":"122c0100-346a-4d8b-b95d-f4a551faecb1","titleType":"Game","platform":"XboxOne","name":"The Swindle","earnedAchievements":1,"currentGamerscore":30,"maxGamerscore":1000},{"lastUnlock":"2016-02-07T14:46:29.9435505Z","titleId":1375792807,"serviceConfigId":"ce6e0100-0173-43e2-a9ed-665d5200eea7","titleType":"Game","platform":"XboxOne","name":"Pool Nation FX","earnedAchievements":2,"currentGamerscore":45,"maxGamerscore":1000},{"lastUnlock":"2017-06-21T17:08:49.6500000Z","titleId":1415041744,"serviceConfigId":"c86b0100-645c-4212-b2e2-fac05457d2d0","titleType":"DGame","platform":"Durango","name":"Tachyon Project","earnedAchievements":1,"currentGamerscore":5,"maxGamerscore":1000},{"lastUnlock":"2017-03-18T20:27:50.2720000Z","titleId":1479999542,"serviceConfigId":"9d7d0100-1df0-49b6-9ef6-659158370036","titleType":"DGame","platform":"Durango","name":"Unravel","earnedAchievements":2,"currentGamerscore":40,"maxGamerscore":1000},{"lastUnlock":"2018-09-13T09:26:54.8580000Z","titleId":1482870140,"serviceConfigId":"a2b70100-d7d8-4f43-8a59-dd4a5862cd7c","titleType":"DGame","platform":"Durango","name":"Warframe","earnedAchievements":7,"currentGamerscore":130,"maxGamerscore":3210},{"lastUnlock":"2017-04-18T16:42:47.1080000Z","titleId":1518572426,"serviceConfigId":"89610100-76bd-4e49-a30a-c2b55a83938a","titleType":"DGame","platform":"Durango","name":"Trackmania\u00ae Turbo","earnedAchievements":4,"currentGamerscore":45,"maxGamerscore":1000},{"lastUnlock":"2015-04-07T17:11:53.3952183Z","titleId":1519874468,"serviceConfigId":"1b180100-2e72-4297-a9e6-b79d5a9771a4","titleType":"DGame","platform":"Durango","name":"Forza Horizon 2 Presents Fast & Furious","earnedAchievements":21,"currentGamerscore":750,"maxGamerscore":1000},{"lastUnlock":"2016-04-26T17:55:11.6426940Z","titleId":1560034050,"serviceConfigId":"3b380100-5867-4ad7-8f08-9b065cfc3b02","titleType":"DGame","platform":"Durango","name":"Assassin's Creed\u00ae Syndicate","earnedAchievements":7,"currentGamerscore":130,"maxGamerscore":1300},{"lastUnlock":"2014-10-31T14:45:49.8906140Z","titleId":1579532320,"serviceConfigId":"88222fc5-b30c-43f2-ab0f-834e9b2266c4","titleType":"DGame","platform":"Durango","name":"Sunset Overdrive","earnedAchievements":4,"currentGamerscore":75,"maxGamerscore":1925},{"lastUnlock":"2019-01-08T19:24:48.4330000Z","titleId":1606375163,"serviceConfigId":"07220100-a9c4-4663-b575-904f5fbf56fb","titleType":"DGame","platform":"Durango","name":"Pinball FX3","earnedAchievements":14,"currentGamerscore":485,"maxGamerscore":1420},{"lastUnlock":"2014-11-04T20:59:29.0000000Z","titleId":1624350228,"serviceConfigId":"d3d00100-7976-472f-a3f7-bc1760d19e14","titleType":"DGame","platform":"Durango","name":"Project Spark","earnedAchievements":7,"currentGamerscore":40,"maxGamerscore":2300},{"lastUnlock":"2019-01-12T12:39:22.4380000Z","titleId":1624494901,"serviceConfigId":"6f950100-5aaf-446d-8998-814160d3d335","titleType":"Game","platform":"XboxOne","name":"The Bridge","earnedAchievements":5,"currentGamerscore":231,"maxGamerscore":1000},{"lastUnlock":"2019-01-01T12:11:11.4170000Z","titleId":1656145947,"serviceConfigId":"00000000-0000-0000-0000-000062b6c81b","titleType":"Game","platform":"XboxOne","name":"Moonlighter","earnedAchievements":45,"currentGamerscore":626,"maxGamerscore":1000},{"lastUnlock":"2016-05-01T10:10:07.7433316Z","titleId":1669682262,"serviceConfigId":"1d6c0100-66bd-491b-afb9-a14163855456","titleType":"Game","platform":"XboxOne","name":"Defense Grid 2","earnedAchievements":14,"currentGamerscore":130,"maxGamerscore":1000},{"lastUnlock":"2017-07-01T10:22:18.9600000Z","titleId":1681220621,"serviceConfigId":"126a0100-20f4-4dfc-a88d-0bf26435640d","titleType":"DGame","platform":"Durango","name":"STAR WARS\u2122 Battlefront\u2122","earnedAchievements":2,"currentGamerscore":30,"maxGamerscore":1690},{"lastUnlock":"2017-01-29T10:29:07.8270000Z","titleId":1708767297,"serviceConfigId":"25629596-d386-444c-a82e-734960c1dea3","titleType":"DGame","platform":"Durango","name":"Ryse: Son of Rome","earnedAchievements":28,"currentGamerscore":740,"maxGamerscore":2000},{"lastUnlock":"2017-12-29T15:17:42.8470000Z","titleId":1799887933,"serviceConfigId":"de360100-3ae5-4fd5-a7da-9d3d6b481c3d","titleType":"DGame","platform":"Durango","name":"The Witcher 3: Wild Hunt","earnedAchievements":4,"currentGamerscore":75,"maxGamerscore":2000},{"lastUnlock":"2015-08-26T13:32:22.8649578Z","titleId":1818736509,"serviceConfigId":"36d70100-472b-47ec-9a55-a44b6c67b77d","titleType":"DGame","platform":"Durango","name":"Pinball FX2","earnedAchievements":3,"currentGamerscore":100,"maxGamerscore":1770},{"lastUnlock":"2016-02-07T09:48:46.8103804Z","titleId":1822336858,"serviceConfigId":"46210100-bc9d-41b4-b84d-76506c9ea75a","titleType":"Game","platform":"XboxOne","name":"Hand of Fate","earnedAchievements":4,"currentGamerscore":60,"maxGamerscore":1330},{"lastUnlock":"2017-06-26T19:15:11.4110000Z","titleId":1824138520,"serviceConfigId":"51930100-3e76-423c-a3f5-78026cba2518","titleType":"DGame","platform":"Durango","name":"Mirror's Edge\u2122 Catalyst","earnedAchievements":24,"currentGamerscore":380,"maxGamerscore":1000},{"lastUnlock":"2018-02-07T17:26:16.1920000Z","titleId":1835497756,"serviceConfigId":"6d6f0100-dc13-45c3-a35e-5c9a6d67791c","titleType":"DGame","platform":"Durango","name":"Agents of Mayhem","earnedAchievements":2,"currentGamerscore":25,"maxGamerscore":1000},{"lastUnlock":"2016-01-14T17:39:21.0789186Z","titleId":1854327039,"serviceConfigId":"769d0100-5c75-4e08-b603-08e86e86c8ff","titleType":"Game","platform":"XboxOne","name":"The Banner Saga","earnedAchievements":6,"currentGamerscore":175,"maxGamerscore":1000},{"lastUnlock":"2016-10-31T17:51:48.1584799Z","titleId":1971898235,"serviceConfigId":"b79a0100-0006-4803-a938-e1d07588c77b","titleType":"Game","platform":"XboxOne","name":"Ziggurat","earnedAchievements":6,"currentGamerscore":95,"maxGamerscore":1000},{"lastUnlock":"2015-09-04T18:25:13.3537783Z","titleId":1989956835,"serviceConfigId":"065e0100-011d-4a3e-a8e0-47e9769c54e3","titleType":"DGame","platform":"Durango","name":"Evolve","earnedAchievements":1,"currentGamerscore":10,"maxGamerscore":1250},{"lastUnlock":"2014-12-23T21:13:40.2701515Z","titleId":1998461943,"serviceConfigId":"02350100-4d36-4975-9147-cbe3771e1bf7","titleType":"DGame","platform":"Durango","name":"Assassin's Creed Unity","earnedAchievements":32,"currentGamerscore":595,"maxGamerscore":1300},{"lastUnlock":"2017-03-18T05:26:23.0310000Z","titleId":2029730324,"serviceConfigId":"cd5f0100-470b-47ba-9540-8c8378fb3a14","titleType":"DGame","platform":"Durango","name":"Mad Max","earnedAchievements":14,"currentGamerscore":92,"maxGamerscore":1000},{"lastUnlock":"2016-12-15T18:05:41.1240000Z","titleId":2038811741,"serviceConfigId":"7fbb0100-3348-45b2-8572-273e7985cc5d","titleType":"Game","platform":"XboxOne","name":"Blue Estate","earnedAchievements":5,"currentGamerscore":150,"maxGamerscore":1000},{"lastUnlock":"2017-01-03T13:45:28.3130000Z","titleId":2052426459,"serviceConfigId":"c4160100-5e93-4b9c-9ff7-41237a558adb","titleType":"DGame","platform":"Durango","name":"EA SPORTS\u2122 FIFA 16","earnedAchievements":2,"currentGamerscore":30,"maxGamerscore":1000},{"lastUnlock":"2019-02-25T18:27:08.1770000Z","titleId":2059211995,"serviceConfigId":"00000000-0000-0000-0000-00007abd14db","titleType":"Game","platform":"XboxOne","name":"Hollow Knight","earnedAchievements":5,"currentGamerscore":25,"maxGamerscore":1000},{"lastUnlock":"2016-05-08T12:43:05.8970863Z","titleId":2061746629,"serviceConfigId":"86270100-8cef-41a9-aaef-d2787ae3c1c5","titleType":"DGame","platform":"Durango","name":"Don't Starve: Giant Edition","earnedAchievements":1,"currentGamerscore":20,"maxGamerscore":1000},{"lastUnlock":"2014-11-04T19:14:38.7088999Z","titleId":2115534787,"serviceConfigId":"8f3c0100-ef10-425c-9f77-9cc67e187fc3","titleType":"Game","platform":"XboxOne","name":"Another World - 20th Anniversary Edition","earnedAchievements":12,"currentGamerscore":1000,"maxGamerscore":1000},{"lastUnlock":"2018-01-01T18:47:57.8700000Z","titleId":2132785815,"serviceConfigId":"f7ac92c7-2fad-4302-a34e-6d869cc1d0ac","titleType":"DGame","platform":"Durango","name":"Wolfenstein\u00ae II: The New Colossus\u2122","earnedAchievements":1,"currentGamerscore":10,"maxGamerscore":1540},{"lastUnlock":"2016-01-01T09:46:59.1113453Z","titleId":2138276496,"serviceConfigId":"dbf90100-3968-4d73-ae27-f7647f738290","titleType":"Game","platform":"XboxOne","name":"Pneuma: Breath of Life","earnedAchievements":1,"currentGamerscore":100,"maxGamerscore":1000},{"lastUnlock":"2015-10-21T19:41:07.2257442Z","titleId":2141647881,"serviceConfigId":"71130100-9817-49a9-a97e-b4387fa6f409","titleType":"DGame","platform":"Durango","name":"Tales from the Borderlands - Episode 1: Zer0 Sum","earnedAchievements":35,"currentGamerscore":1000,"maxGamerscore":1000}],"pagingInfo":{"continuationToken":null,"totalRecords":199}}